[
    {
        "C\u00f3digo": "8969",
        "Fecha": "26/07/2023 13:42:15",
        "Encargado": "RIBANA RUTH REA RUEDA",
        "Total Bs.": "200,724.10",
        "Tipo": "EMPRESA TRANSPORTADORA",
        "Estado": "ACTIVO",
        "Recaudadora": "LA PAZ"
    },
    {
        "C\u00f3digo": "8961",
        "Fecha": "25/07/2023 17:43:21",
        "Encargado": "RIBANA RUTH REA RUEDA",
        "Total Bs.": "187,331.20",
        "Tipo": "EMPRESA TRANSPORTADORA",
        "Estado": "ACTIVO",
        "Recaudadora": "LA PAZ"
    },
    {
        "C\u00f3digo": "8951",
        "Fecha": "24/07/2023 13:56:54",
        "Encargado": "RIBANA RUTH REA RUEDA",
        "Total Bs.": "339,590.60",
        "Tipo": "EMPRESA TRANSPORTADORA",
        "Estado": "ACTIVO",
        "Recaudadora": "LA PAZ"
    },
    {
        "C\u00f3digo": "8939",
        "Fecha": "21/07/2023 14:01:58",
        "Encargado": "RIBANA RUTH REA RUEDA",
        "Total Bs.": "175,016.10",
        "Tipo": "EMPRESA TRANSPORTADORA",
        "Estado": "ACTIVO",
        "Recaudadora": "LA PAZ"
    },
    {
        "C\u00f3digo": "8932",
        "Fecha": "20/07/2023 14:29:27",
        "Encargado": "RIBANA RUTH REA RUEDA",
        "Total Bs.": "279,121.20",
        "Tipo": "EMPRESA TRANSPORTADORA",
        "Estado": "ACTIVO",
        "Recaudadora": "LA PAZ"
    },
    {
        "C\u00f3digo": "8925",
        "Fecha": "19/07/2023 12:49:10",
        "Encargado": "RIBANA RUTH REA RUEDA",
        "Total Bs.": "327,620.72",
        "Tipo": "EMPRESA TRANSPORTADORA",
        "Estado": "ACTIVO",
        "Recaudadora": "LA PAZ"
    }
]